modchem/__init__.py
modchem/catalogs/elements.py
modchem/commands/__init__.py
modchem/commands/command.py
modchem/database/datasets.py
modchem/entities/atom.py
modchem/entities/ion.py
modchem/entities/molecula.py
modchem/experiment/experimental.py
modchem/seccion/seccion.py
modchem-0.0.6.dist-info/METADATA
modchem-0.0.6.dist-info/WHEEL
modchem-0.0.6.dist-info/entry_points.txt
modchem-0.0.6.dist-info/top_level.txt
modchem-0.0.6.dist-info/RECORD
