Metadata-Version: 2.4
Name: modchem
Version: 0.0.6
Summary: Library for registration chemistry experiment
Author-email: Modestra <kirillkarachev04@gmail.com>
Keywords: science,chem,chemistry
Classifier: Programming Language :: Python :: 3
Classifier: License :: OSI Approved :: MIT License
Classifier: Operating System :: OS Independent
Requires-Python: >=3.10.0
Requires-Dist: argparse>=1.4.0
Requires-Dist: Events>=0.5
Requires-Dist: requests>=2.32.5
